{
  "organizations": [
    {
      "sr": 1,
      "nickname": "મણિનગર ઉપાશ્રય",
      "name": "શ્રી મણિનગર સ્થાનકવાસી જૈન સંઘ",
      "address": "રાવજીભાઈ ટાવર પાસે, કૃષ્ણબાગ, મણિનગર, અમદાવાદ - ૮",
      "secretary_mobile": "9374621115",
      "sadhvis": [
        "સુવ્યાખ્યાની બા.બ્ર.પ.પૂ. આજ્ઞાકુમારીજી મ.સ.",
        "કાર્યદક્ષ બા.બ્ર.પ.પૂ. યશસ્વિનીકુમારીજી મ.સ.",
        "જ્ઞાન પિપાસુ બા.બ્ર.પ.પૂ. સ્વીકૃતિકુમારીજી મ.સ."
      ]
    },
    {
      "sr": 2,
      "nickname": "રાજસ્થાન એસ.એસ.",
      "name": "શ્રી રાજસ્થાન સ્થાનકવાસી જૈન સંઘ (શ્રી રાજસ્થાન એસ.એસ. જૈન સંઘ)",
      "address": "મહાવીર ભવન, ૯-એ,૧૦-બી શ્રી હરીનગર કો.ઓ. હા.સો., ઢોર બજાર કાંકરિયા, અમદાવાદ - ૨૨",
      "secretary_mobile": "9825015219",
      "sadhvis": [
        "મહાસાધ્વી ડૉ. સુપ્રભાજી મ.સા. સુધા",
        "સાધ્વી ડૉ શ્રી ઉદિતપ્રભાજી મ.સા. ઉષા",
        "સાધ્વી ડૉ શ્રી હેમપ્રભાજી મ.સા. હિમાંશુ",
        "સાધ્વી ડૉ શ્રી ઇમિતપ્રભાજી મ.સા.",
        "સાધ્વી શ્રી ઉન્નતિપ્રભાજી મ.સા.",
        "સાધ્વી શ્રી નીલેશ પ્રભાજી મ.સા."
      ]
    },
    {
      "sr": 3,
      "nickname": "વાસણા ઉપાશ્રય",
      "name": "શ્રી વર્ધમાન સ્થાનકવાસી જૈન સંઘ (શ્રી જશવંતલાલ ગીરધરલાલ શાહ (ટુવાવાળા) શ્રી સંત સતીજી આવાસ)",
      "address": "૭, સુંદરવન સોસાયટી, બંસીધર સોસાયટી સામે, જવાહરનગર, વાસણા, અમદાવાદ - ૭",
      "secretary_mobile": "9227888000",
      "sadhvis": [
        "બા.બ્ર.પ.પૂ. સંગીતાબાઈ મ.સ.",
        "બા.બ્ર.પ.પૂ. ભાવનાબાઈ મ.સ.",
        "બા.બ્ર.પ.પૂ. વિરતીબાઈ મ.સ.",
        "બા.બ્ર.પ.પૂ. પ્રેક્ષાબાઈ મ.સ."
      ]
    },
    {
      "sr": 4,
      "nickname": "એલિસબ્રીજ ઉપાશ્રય",
      "name": "શ્રી એલિસબ્રીજ સ્થાનકવાસી જૈન સંઘ",
      "address": "શેઠ શ્રી ચમનલાલ ઉમેદચંદ શાહ પાટીવાળા જૈન ઉપાશ્રય, નૂતન નાગરીક બેન્કની સામે, નારાયણનગર રોડ, શાંતિવન, પાલડી, અમદાવાદ - ૩૮૦ ૦૦૭",
      "secretary_mobile": "9429303088",
      "sadhvis": [
        "આધ્યાત્મયોગીની બા.બ્ર.પ.પૂ. પ્રેમલભગવાન",
        "પૂ. ચંદ્રેશાબાઈ મ.સ.",
        "બા.બ્ર.પ.પૂ. ભાવેશાબાઈ મ.સ.",
        "બા.બ્ર.પ.પૂ. ધૈર્યતાબાઈ મ.સ.",
        "બા.બ્ર.પ.પૂ. સૌમ્યતાબાઈ મ.સ.",
        "બા.બ્ર.પ.પૂ. સ્વાતિબાઈ મ.સ.",
        "પૂ. પવિત્રાબાઈ મ.સ.",
        "બા.બ્ર.પ.પૂ. પૂર્વાંશીબાઈ મ.સ."
      ]
    },
    {
      "sr": 5,
      "nickname": "નવલપ્રકાશ જૈન ઉપાશ્રય",
      "name": "શ્રી નવલ-પ્રકાશ જૈન ઉપાશ્રય (શ્રીમતી ભાગ્યવતી જગશીભાઈ સામત ગાલા ભચાઉવાળા)",
      "address": "ઋષભ ફ્લેટની બાજુમાં, એચ.કે. કોમ્પલેક્ષની ગલીમાં, વિ.આર. શાહ સ્કુલ પાસે, ભઠ્ઠા પાલડી, અમદાવાદ-૩૮૦૦૦૭",
      "secretary_mobile": "9825065599",
      "sadhvis": [
        "સરળ સ્વભાવી પ.પૂ. ધર્મેચ્છાકુમારીજી મ.સ.",
        "સુવ્યાખ્યાની પ.પૂ. ધન્યતાકુમારીજી મ.સ."
      ]
    },
    {
      "sr": 6,
      "nickname": "ચંપકગુરુ જૈન આ. ભવન",
      "name": "શ્રી ચંપકગુરુ સ્થા. જૈન આરાધના ભવન",
      "address": "ગ્રા. ફલોર, રાજયશ, સિલ્વર ફલોરા પાસે, ન્યુ વાસણા, અમદાવાદ-૩૮૨૪૬૦",
      "secretary_mobile": "9825032685",
      "sadhvis": [
        "બા.બ્ર.પ.પૂ. મુદુતાજી મ.સ.",
        "બા.બ્ર.પ.પૂ. દિવ્યતાજી મ.સ."
      ]
    },
    {
      "sr": 7,
      "nickname": "લાવણ્ય ઉપાશ્રય",
      "name": "શ્રી લાવણ્ય ઉપાશ્રય (શ્રી દરિયાપુરી સ્થાનકવાસી જૈન સમિતિ સંચાલિત, પાલનપુર નિવાસી શ્રી હરિભાઈ જશકરણભાઈ મહેતા સ્થા.જૈન ઉપાશ્રય)",
      "address": "૪૨, લાવણ્ય સોસાયટી, વાસણા, અમદાવાદ-૭",
      "secretary_mobile": "9825455800",
      "sadhvis": [
        "બા.બ્ર.પ.પૂ. શ્રી નેહાબાઈ મ.સ.",
        "બા.બ્ર.પ.પૂ. શ્રી શ્રેયાબાઈ મ.સ."
      ]
    },
    {
      "sr": 8,
      "nickname": "જીવરાજપાર્ક ઉપાશ્રય",
      "name": "શ્રી જીવરાજપાર્ક ઉપાશ્રય (શ્રી સ્થાનકવાસી જૈન સંઘ, જીવરાજ પાર્ક - શેઠ હરીલાલ ઓઘડભાઈ ગોસલીયા સ્થા. જૈન ઉપાશ્રય)",
      "address": "આશાપુરી ફ્લેટ પાસે, જીવરાજ પાર્ક, અમદાવાદ - ૩૮૦ ૦૫૧",
      "secretary_mobile": "9824394775",
      "sadhvis": [
        "મધુર વ્યાખ્યાની બા.બ્ર.પ.પૂ. સુજાબાઈ મ.સ.",
        "સ્વધર્મી પ્રેમી બા.બ્ર.પ.પૂ. હર્ષજાબાઈ મ.સ.",
        "સેવાભાવી બા.બ્ર.પ.પૂ. મિતજાબાઈ મ.સ."
      ]
    },
    {
      "sr": 9,
      "nickname": "આંબાવાડી ઉપાશ્રય",
      "name": "શ્રી સ્થાનકવાસી જૈન સંઘ, આંબાવાડી (શેઠ વૃંદાવનદાસ વલ્લભદાસ મહેતા સ્થા. જૈન ઉપાશ્રય)",
      "address": "૨, આમ્રકુંજ સોસાયટી, સ્નેહકુંજ બસ સ્ટેન્ડ પાસે, નહેરુનગર પાસે, આંબાવાડી, અમદાવાદ - ૧૫",
      "secretary_mobile": "9429003972",
      "sadhvis": [
        "બા.બ્ર.પ.પૂ. હંસાબાઈ મહાસતીજી (મોટા)",
        "સાધ્વી શ્રી રસીલાકુમારી આર્યાજી",
        "સાધ્વી શ્રી અંજલીકુમારી આર્યાજી",
        "સાધ્વી શ્રી નયનાકુમારી આર્યાજી",
        "સાધ્વી શ્રી દર્શનાશ્રી આર્યાજી"
      ]
    },
    {
      "sr": 10,
      "nickname": "સેટેલાઇટ ઉપાશ્રય",
      "name": "શ્રી સેટેલાઈટ ઉપાશ્રય (શ્રી સ્થાનકવાસી જૈન સંઘ - સેટેલાઈટ)",
      "address": "અશ્વમેઘ, વિ-૪/બી, એક્સટેન્શન, સૃષ્ટિ બંગલા પાસે, સેટેલાઈટ ૧૩૨ ફૂટ રીંગ રોડ, અમદાવાદ -૩૮૦૦૧૫",
      "secretary_mobile": "9377968686",
      "sadhvis": [
        "બા.બ્ર.પ.પૂ. પ્રતિભાબાઈ મ.સ.",
        "બા.બ્ર.પ.પૂ. ફાલ્ગુનીબાઈ મ.સ.",
        "બા.બ્ર.પ.પૂ. કૃપાલીબાઈ મ.સ.",
        "બા.બ્ર.પ.પૂ. નીપાબાઈ મ.સ.",
        "બા.બ્ર.પ.પૂ. ખુશાલીબાઈ મ.સ."
      ]
    },
    {
      "sr": 11,
      "nickname": "જોધપુર પ્રેરણા વિરાજ",
      "name": "શ્રી દરિયાપુરી સ્થાનકવાસી જૈન ટ્રસ્ટ સંચાલિત પ્રેરણા વિરાજ (શ્રી સ્થાનકવાસી જૈન સંઘ જોધપુર અમદાવાદ, માતુશ્રી કાંતાબેન ચીમનલાલ સંઘવી ઉપાશ્રય)",
      "address": "પ્રેરણા વિરાજ ટાવર, ૧એ-વિંગ, ઔડા પમ્પીંગ સ્ટેશન પાસે, રોજવુડ એસ્ટેટ સામે, જોધપુર, સેટેલાઈટ, અમદાવાદ-૧૫",
      "secretary_mobile": "9429004492",
      "sadhvis": [
        "બા.બ્ર.પ.પૂ. ભાનુબાઈ મ.સ.",
        "બા.બ્ર.પ.પૂ. ભાવનાબાઈ મ.સ.",
        "બા.બ્ર.પ.પૂ. મનીષાબાઈ મ.સ.",
        "બા.બ્ર.પ.પૂ.રત્નેષાબાઈ મ.સ."
      ]
    },
    {
      "sr": 12,
      "nickname": "ધર્માલય સ્થા. જૈન ઉપાશ્રય",
      "name": "ધર્માલય સ્થાનકવાસી જૈન ઉપાશ્રય (શ્રીમતી ગુણીબેન રજનીભાઈ મહેતા ચેરીટેબલ ટ્રસ્ટ સંચાલિત)",
      "address": "કિર્તીસાગર ફ્લેટની બાજુમાં, ઓમકારેશ્વર મહાદેવ પાસે, મહારાજ કોમ્પલેક્ષની સામે, બાલાજી ચાર રસ્તા, જોધપુર-સેટેલાઈટ, અમદાવાદ -૩૮૦૦૧૫",
      "secretary_mobile": "9898788309",
      "sadhvis": [
        "પ.પૂ. સુધાબાઈ મ.સ.",
        "પ.પૂ. જયોત્સનાબાઈ મ.સ.",
        "પ.પૂ. મીનાબાઈ મ.સ.",
        "પ.પૂ. જાગૃતિબાઈ મ.સ.",
        "પ.પૂ. પ્રભુતાજી મ.સ.",
        "પ.પૂ. સૌમ્યતાજી મ.સ."
      ]
    },
    {
      "sr": 13,
      "nickname": "આનંદનગર ઉપાશ્રય",
      "name": "શ્રી આનંદનગર (સેટેલાઈટ) ઉપાશ્રય (શ્રીમતી રંજનબેન રજનીકાન્તભાઈ જોબાલીયા ધર્મસ્થાનક)",
      "address": "શેલ પેટ્રોલ પંપની સામેની ગલીમાં, ઈશાન-૩ની બાજુમાં, યુરોકિટ સ્કૂલની સામે, આનંદ નગર સેટેલાઈટ, અમદાવાદ-૩૮૦૦૧૫",
      "secretary_mobile": "9825184663",
      "sadhvis": [
        "સ્વાધ્યાય પ્રેમી બા.બ્ર.પ.પૂ. ઉષાજી મ.સ.",
        "બા.બ્ર.પ.પૂ. નમ્રતાજી મ.સ.",
        "બા.બ્ર.પ.પૂ. સુજાતાજી મ.સ.",
        "બા.બ્ર.પ.પૂ. કૌમુદિનીજી મ.સ.",
        "બા.બ્ર.પ.પૂ. જ્યોતિજી મ.સ.",
        "બા.બ્ર.પ.પૂ. હિતસ્વિનીજી મ.સ.",
        "બા.બ્ર.પ.પૂ. રિધ્ધિજી મ.સ."
      ]
    },
    {
      "sr": 14,
      "nickname": "બોપલ ઉપાશ્રય",
      "name": "શ્રી વર્ધમાન સ્થાનકવાસી જૈન સંઘ ટ્રસ્ટ (આંબલી-બોપલ-ઘુમા)",
      "address": "પ્લોટ નં. ૭, રાજપથનગર, દીપકલા એન્કલેવ સામે, રવિ સ્કૂલ પાસે, એચપીસીએલ પેટ્રોલપંપની ગલીમાં, બોપલ, અમદાવાદ-૫૮",
      "secretary_mobile": "9727789696",
      "sadhvis": [
        "બા.બ્ર.પ.પૂ. સવિતાબાઈ મ.સ.",
        "બા.બ્ર.પ.પૂ. ઉર્મિલાબાઈ મ.સ.",
        "બા.બ્ર.પ.પૂ. મૌલિબાઈ મ.સ."
      ]
    },
    {
      "sr": 15,
      "nickname": "સાઉથ બોપલ ઉપાશ્રય",
      "name": "શ્રી સાઉથ બોપલ સ્થાનકવાસી જૈન સંઘ (શ્રી ધર્મસિંહજી સ્વામી સ્થાનકવાસી જૈન ઉપાશ્રય)",
      "address": "એ-૪૦, સ્પ્રીંગ મિડોઝ બંગ્લોઝ રામદેવ ઘંટીની પાસે, ગાલા જીમખાના રોડ, સી.બી. સેન્ટર ચાર રસ્તા, સાઉથ બોપલ, અમદાવાદ-૩૮૦૦૫૮",
      "secretary_mobile": "9374807508",
      "sadhvis": [
        "બા.બ્ર.પ.પૂ. અમિતાબાઈ મ.સ.",
        "બા.બ્ર.પ.પૂ. વિભાબાઈ મ.સ."
      ]
    },
    {
      "sr": 16,
      "nickname": "કાઠીયાવાડી સ્થા. જૈન સમાજ-બોપલ",
      "name": "શ્રી ધર્મનાથ સ્થાનકવાસી જૈન સંઘ (શ્રી કાઠિયાવાડ સ્થા. જૈન સમાજ, અમદાવાદ)",
      "address": "શિવાલિક સત્યમેવની પાછળ, વકીલ સાહેબ બ્રિજ પાસે, મેકડોનાલ્ડ્સની ગલીમાં, હરિઓમ બંગલોની બાજુમાં, આંબલી-બોપલ કોસ રોડ, બોપલ, અમદાવાદ-૩૮૦૦૫૮",
      "secretary_mobile": "9824653555",
      "sadhvis": [
        "પરમશ્રી વિનમ્ર મુનિ મ.સા.",
        "પરમશ્રી પવિત્ર મુનિ મ.સા.",
        "પરમશ્રી સોહમ મુનિ મ.સા."
      ]
    },
    {
      "sr": 17,
      "nickname": "વસ્ત્રાપુર ઉપાશ્રય",
      "name": "શ્રી વર્ધમાન સ્થાનકવાસી જૈન સંઘ-વસ્ત્રાપુર સંચાલિત (માતૃશ્રી શાંતાબેન મનુભાઈ શેઠ ઉપાશ્રય)",
      "address": "૨૦૩, નહેરુપાર્ક, સરદાર સેન્ટર પાછળ, હિલ્લોરા રેસીડેન્સીની બાજુમાં, વસ્ત્રાપુર, અમદાવાદ-૩૮૦૦૧૫",
      "secretary_mobile": "9725461122",
      "sadhvis": [
        "શાસન દીપિકા સાધ્વી પ.પૂ. શ્રી રામધ્વનિ શ્રીજી મ.સ.",
        "પ.પૂ. શ્રી રામનિધિ શ્રીજી મ.સ.",
        "પ.પૂ. શ્રી રામનેમિ શ્રીજી મ.સ.",
        "પ.પૂ. શ્રી રામસ્મૃતિ શ્રીજી મ.સ."
      ]
    },
    {
      "sr": 18,
      "nickname": "થલતેજ ઉપાશ્રય",
      "name": "શ્રી થલતેજ ઉપાશ્રય (શ્રી થલતેજ સ્થાનકવાસી જૈન સંઘ, શ્રી દરિયાપુરી સ્થાનકવાસી જૈન સમિતિ સંચાલિત)",
      "address": "૩, સર્વેશ્વર ટાવર, લવકુશ ટાવરની બાજુમાં, જયઅંબેનગરની સામે, થલતેજ ટેકરા, અમદાવાદ - ૩૮૦ ૦૫૪",
      "secretary_mobile": "9265188985",
      "sadhvis": [
        "મધુરવ્યાખ્યાતા બા.બ્ર.પ.પૂ. પુષ્પાબાઈ મ.સ.",
        "બા.બ્ર.પ.પૂ. ભારતીબાઈ મ.સ.",
        "પ.પૂ. તુભ્યવીબાઈ મ.સ."
      ]
    },
    {
      "sr": 19,
      "nickname": "મેમનગર ઉપાશ્રય",
      "name": "શ્રી મેમનગર ઉપાશ્રય (શ્રી મેમનગર સ્થાનકવાસી જૈન સંઘ, શ્રી જશવંતલાલ ગીરધરલાલ શાહ ટુવાવાળા સ્થા. જૈન ઉપાશ્રય)",
      "address": "જૈનાચાર્ય અજરામર માર્ગ સુભાષચોક, મેમનગર, અમદાવાદ -૫૨",
      "secretary_mobile": "9426827195",
      "sadhvis": [
        "બા.બ્ર.પ.પૂ. સુશીલાબાઈ મ.સ.",
        "બા.બ્ર.પ.પૂ. જ્યોતિબાઈ મ.સ.",
        "બા.બ્ર.પ.પૂ. ભારતીબાઈ મ.સ.",
        "બા.બ્ર.પ.પૂ. રિધ્ધિબાઈ મ.સ.",
        "બા.બ્ર.પ.પૂ. ધ્રુવીબાઈ મ.સ."
      ]
    },
    {
      "sr": 20,
      "nickname": "નવરંગપુરા ઉપાશ્રય",
      "name": "શ્રી નવરંગપુરા ઉપાશ્રય (શ્રી સ્થાનકવાસી જૈન સંઘ, નવરંગપુરા)",
      "address": "સ્વપ્નિલ ૫ ની ગલીમાં મેટ્રો સ્ટેશન પાસે, કોમર્સ કોલેજ છ રસ્તા, ડ્રાઈવઈન રોડ, નવરંગપુરા",
      "secretary_mobile": "9376124435",
      "sadhvis": [
        "બા.બ્ર.પ.પૂ. ગીતાજી મ.સ.",
        "બા.બ્ર.પ.પૂ. સુદિશાજી મ.સ.",
        "બા.બ્ર.પ.પૂ. ઋજુતાજી મ.સ.",
        "બા.બ્ર.પ.પૂ. ઉન્નતિજી મ.સ."
      ]
    },
    {
      "sr": 21,
      "nickname": "સોલા ઉપાશ્રય",
      "name": "શ્રી સોલા ઉપાશ્રય (શ્રી સોલારોડ સ્થાનકવાસી જૈન સંઘ)",
      "address": "સુંદરવન એપાર્ટમેન્ટ પાછળ, પેટ્રોલ પંપ સામેની ગલીમાં, આદીનાથ જૈન દેરાસર સામે, સોલારોડ, અમદાવાદ - ૬૩",
      "secretary_mobile": "7698571234",
      "sadhvis": [
        "બા.બ્ર.પ.પૂ. ઈલાબાઈ મ.સ.",
        "બા.બ્ર.પ.પૂ. ડૉ. નીલાબાઈ મ.સ.",
        "બા.બ્ર.પ.પૂ. રંજનબાઈ મ.સ.",
        "બા.બ્ર.પ.પૂ. સાધનાબાઈ મ.સ.",
        "બા.બ્ર.પ.પૂ. વીણાબાઈ મ.સ."
      ]
    },
    {
      "sr": 22,
      "nickname": "ઘાટલોડીયા ઉપાશ્રય",
      "name": "શ્રી ઘાટલોડિયા ઉપાશ્રય (શ્રી વર્ધમાન સ્થાનકવાસી જૈન સંઘ)",
      "address": "એ-૮૩, શ્રીકુંજ શોપિંગ સેન્ટર, સમર્પણ ટાવર સામે, પંચેશ્વર મંદિર, ઘાટલોડિયા, અમદાવાદ-૬૧",
      "secretary_mobile": "9979925128",
      "sadhvis": [
        "શ્રમણી શ્રેષ્ઠ બા.બ્ર.પ.પૂ. ભારતીજી મ.સ.",
        "બા.બ્ર.પ.પૂ. જિજ્ઞાસાજી મ.સ.",
        "બા.બ્ર.પ.પૂ. કલ્યાણીજી મ.સ.",
        "બા.બ્ર.પ.પૂ. ધૈર્યતાજી મ.સ."
      ]
    },
    {
      "sr": 23,
      "nickname": "નિર્ણયનગર ઉપાશ્રય",
      "name": "શ્રી નિર્ણયનગર ઉપાશ્રય (નિર્ણયનગર સ્થાનકવાસી જૈન સંઘ)",
      "address": "બી-૧૬, કામધેનુ કોમ્પલેક્ષ, અર્જુન આશ્રમ રોડ, ગ્રીન સીટી સામે, નિર્ણયનગર રોડ, અમદાવાદ-૩૮૨૪૮૧",
      "secretary_mobile": "8000445348",
      "sadhvis": [
        "પ.પૂ. અક્ષિતાજી મ.સ.",
        "પ.પૂ. અંકિતાજી મ.સ."
      ]
    },
    {
      "sr": 24,
      "nickname": "કલ્પતરૂ ઉપાશ્રય (ભાસ્કર)",
      "name": "શ્રી કલ્પતરૂ ઉપાશ્રય (શ્રી મીરામ્બીકારોડ સ્થા. જૈન સંઘ, શ્રી દરિયાપુરી સ્થાનકવાસી જૈન સમિતિ સંચાલિત)",
      "address": "૩, કલ્પતરૂ સોસાયટી, મીરામ્બિકા સ્કૂલ રોડ, નારણપુરા, અમદાવાદ - ૩૮૦૦૧૩",
      "secretary_mobile": "9426059657",
      "sadhvis": [
        "બા.બ્ર.પ.પૂ. પ્રેક્ષાબાઈ મ.સ.",
        "બા.બ્ર.પ.પૂ. દ્રષ્ટાબાઈ મ.સ.",
        "બા.બ્ર.પ.પૂ. સુહાનીબાઈ મ.સ.",
        "બા.બ્ર.પ.પૂ. વંદિનીબાઈ મ.સ."
      ]
    },
    {
      "sr": 25,
      "nickname": "વિજયનગર ઉપાશ્રય",
      "name": "શ્રી વિજયનગર ઉપાશ્રય (શ્રી શાહપુર દરિયાપુરી આઠ કોટી સ્થા. જૈન સંઘ સંચાલિત, શ્રી વિજયનગર સ્થાનકવાસી જૈન મંડળ)",
      "address": "૮૯/૫૨૯, વિજયનગર ફ્લેટ, નારણપુરા વિજયનગર, અમદાવાદ ૧૩",
      "secretary_mobile": "9825203254",
      "sadhvis": [
        "બા.બ્ર.પ.પૂ. કરુણાબાઈ મ.સ.",
        "બા.બ્ર.પ.પૂ. રેખાબાઈ મ.સ.",
        "બા.બ્ર.પ.પૂ. ધર્મિષ્ઠાબાઈ મ.સ.",
        "બા.બ્ર.પ.પૂ. સિધ્ધિબાઈ મ.સ.",
        "બા.બ્ર.પ.પૂ. પ્રતિતીબાઈ મ.સ."
      ]
    },
    {
      "sr": 26,
      "nickname": "અજરામર સ્થા. જૈન સંઘ",
      "name": "અજરામર સ્થા. જૈન સંઘ અંકુર, અમદાવાદ (માતુશ્રી મધુબેન મનસુખલાલ ગુલાબચંદ શાહ ટોકરાણાવાળા અજરામર જૈન ઉપાશ્રય)",
      "address": "૨, કામદુર્ગા સોસાયટી, વિ-૨, અંકુર ચાર રસ્તા પાસે, અંકુર, નારણપુરા, અમદાવાદ-૧૩",
      "secretary_mobile": "9426513738",
      "sadhvis": [
        "પ.પૂ.શ્રી અમરલતાજી આર્યાજી",
        "પ.પૂ.શ્રી ભક્તિકુમારી આર્યાજી",
        "પ.પૂ.શ્રી પ્રતિક્ષાકુમારી આર્યાજી",
        "પ.પૂ.શ્રી તિતીક્ષાકુમારી આર્યાજી",
        "પ.પૂ.શ્રી ઉર્જાકુમારી આર્યાજી",
        "પ.પૂ.શ્રી પ્રિયંવદાજી આર્યાજી"
      ]
    },
    {
      "sr": 27,
      "nickname": "નારણપુરા ઉપાશ્રય",
      "name": "શ્રી નારણપુરા ઉપાશ્રય (શ્રી લક્ષ્મીચંદ ઝવેરચંદ સંઘવી સ્થાનકવાસી જૈન ઉપાશ્રય, શ્રી ચંદુલાલ છગનલાલ શાહ સ્થાનકવાસી જૈન ધર્મસ્થાનક)",
      "address": "૨૮/૨૯, સ્થા. જૈન સોસાયટી, રેલ્વે કોસીંગ પાસે, નારણપુરા, અમદાવાદ-૩૮૦૦૧૩",
      "secretary_mobile": "9408230127",
      "sadhvis": [
        "બા.બ્ર.પ.પૂ. મધુબાઈ મ.સ.",
        "બા.બ્ર.પ.પૂ. રંજનબાઈ મ.સ.",
        "બા.બ્ર.પ.પૂ. ભાવનાબાઈ મ.સ.",
        "બા.બ્ર.પ.પૂ. હિતજ્ઞાબાઈ મ.સ.",
        "બા.બ્ર.પ.પૂ. મોક્ષાબાઈ મ.સ.",
        "બા.બ્ર.પ.પૂ. મિતેષાબાઈ મ.સ."
      ]
    },
    {
      "sr": 28,
      "nickname": "તારાબાઈ આર્યાજી ઉપાશ્રય",
      "name": "શ્રી તારાબાઈ આર્યાજી સિદ્ધાંત ટ્રસ્ટ",
      "address": "ઝવેરી પાર્ક, સ્થાનકવાસી જૈન ધર્મસ્થાનક પાસે, નારણપુરા રેલ્વે કોસીંગ પાસે, નારણપુરા, અમદાવાદ - ૩૮૦૦૧૩",
      "secretary_mobile": "8320265994",
      "sadhvis": [
        "બા.બ્ર.પ.પૂ. હર્ષાબાઈ મ.સ.",
        "બા.બ્ર.પ.પૂ. જયશ્રીબાઈ મ.સ.",
        "બા.બ્ર.પ.પૂ.પ્રેરણાબાઈ મ.સ.",
        "બા.બ્ર.પ.પૂ. નયનાબાઈ મ.સ."
      ]
    },
    {
      "sr": 29,
      "nickname": "બોતાદ સ્થા. જૈન સંઘ",
      "name": "શ્રી બોટાદ સંપ્રદાય સ્થા. જૈન સંઘ",
      "address": "૧૬/૨ દેવેન્દ્રપાર્ક સોસા., અમીકુંજ સોસા પાસે, નારણપુરા, અમદાવાદ - ૩૮૦૦૧૩",
      "secretary_mobile": "6355048579",
      "sadhvis": [
        "બા.બ્ર.પ.પૂ. મધુબાઈ મ.સ.",
        "બા.બ્ર.પ.પૂ. હંસાબાઈ મ.સ.",
        "બા.બ્ર.પ.પૂ. રેણુકાબાઈ મ.સ.",
        "બા.બ્ર.પ.પૂ. દિપીકાબાઈ મ.સ.",
        "બા.બ્ર.પ.પૂ. જિનાજ્ઞાબાઈ મ.સ."
      ]
    },
    {
      "sr": 30,
      "nickname": "નવાવાડજ ઉપાશ્રય",
      "name": "શ્રી નવાવાડજ ઉપાશ્રય (શ્રી સ્થાનકવાસી જૈન સંઘ - નવા વાડજ, શેઠશ્રી રતિલાલ વિઠ્ઠલદાસ ગોસલીયા (ગઢડા નિવાસી) સ્થા. જૈન ઉપાશ્રય)",
      "address": "ચંપકનગર ફ્લેટની બાજુમાં નવા વાડજ, સ્વસ્તિક સ્કૂલ સામે, અમદાવાદ-૩૮૦૦૧૩",
      "secretary_mobile": "9879090279",
      "sadhvis": [
        "બા.બ્ર.પ.પૂ. ચારૂબાઈ મ.સ.",
        "બા.બ્ર.પ.પૂ. અનિલાબાઈ મ.સ.",
        "બા.બ્ર.પ.પૂ. ભાવનાબાઈ મ.સ.",
        "બા.બ્ર.પ.પૂ. હેમાબાઈ મ.સ.",
        "બા.બ્ર.પ.પૂ. પ્રિયંકરાબાઈ મ.સ.",
        "નૂતન દિક્ષીત બા.બ્ર.પ.પૂ. વીરહેમશ્રીજી મ.સ."
      ]
    },
    {
      "sr": 31,
      "nickname": "દેવભૂમિ સ્થા. જૈન ઉપાશ્રય",
      "name": "શ્રી દેવભૂમિ સ્થાનકવાસી જૈન સંઘ",
      "address": "ડૉ. કસ્તુરચંદ બાલાભાઈ આરાધનાભવન, દેવભૂમિ એપાર્ટમેન્ટની બાજુમાં, સત્તાધાર ચાર રસ્તા પાસે, ઘાટલોડિયા, અમદાવાદ-૬૧",
      "secretary_mobile": "9499847247",
      "sadhvis": [
        "બા.બ્ર.પ.પૂ. શ્રીઅર્પણાબાઈ મ.સ.",
        "બા.બ્ર.પ.પૂ. શ્રી હંસાબાઈ મ.સ.",
        "બા.બ્ર.પ.પૂ. શ્રી કવિજ્ઞાબાઈ મ.સ."
      ]
    },
    {
      "sr": 32,
      "nickname": "અજરામર સ્થા. જૈન સંઘ (ચાણક્યપુરી)",
      "name": "શ્રી અજરામર સ્થાનકવાસી જૈન સંઘ - ચાણક્યપુરી",
      "address": "ગ્રાઉન્ડ ફ્લોર, એલ.બી ટાવર, સેક્ટર નં.-૬ જે.જે. હોસ્પિટલ પાસે, ચાણક્યપુરી, અમદાવાદ-૬૧",
      "secretary_mobile": "9099980145",
      "sadhvis": [
        "પ.પૂ. શ્રી તરૂલતાજી મ.સ.",
        "પ.પૂ. શ્રી ઉષાકુમારી મ.સ."
      ]
    },
    {
      "sr": 33,
      "nickname": "ઘનશ્યામનગર ઉપાશ્રય",
      "name": "શ્રી ઘનશ્યામનગર ઉપાશ્રય (પ.પૂ. આચાર્યશ્રી નાગચંદ્રજી સ્વામી જૈનજ્ઞાન મંદિર, શ્રી ઘનશ્યામનગર સ્થાનકવાસી જૈન સંઘ)",
      "address": "વાય-૪, ઘનશ્યામનગર સોસાયટી, સુભાષબ્રિજના નાકે આર.ટી.ઓ. સામે, આશ્રમ રોડ, અમદાવાદ-૩૮૦૦૨૭",
      "secretary_mobile": "9898055118",
      "sadhvis": []
    },
    {
      "sr": 34,
      "nickname": "શાહીબાગ ઉપાશ્રય (સુજાતા)",
      "name": "શ્રી શાહીબાગ ઉપાશ્રય (શ્રી શાહીબાગ સ્થાનકવાસી જૈન સંઘ)",
      "address": "એ૧/૨, સુજાતા ફ્લેટ તેરાપંથ ભવન સામે, કેમ્પ રોડ, શાહીબાગ, અમદાવાદ - ૩૮૦ ૦૦૪",
      "secretary_mobile": "9825323225",
      "sadhvis": [
        "સ્વાધ્યાયપ્રેમી બા.બ્ર.પ.પૂ. મનોરમાજી મ.સ.",
        "આગમરત્ના બા.બ્ર.પ.પૂ. નીરુપમાજી મ.સ.",
        "ગુરુકૃપા પાત્રી બા.બ્ર.પ.પૂ. કૃપાલીજી મ.સ.",
        "નિજાનંદી બા.બ્ર.પ.પૂ. નીરાલીજી મ.સ.",
        "મધુરકંઠી બા.બ્ર.પ.પૂ. ભાવીજ્ઞાજી મ.સ."
      ]
    },
    {
      "sr": 35,
      "nickname": "ગીરધરનગર ઉપાશ્રય",
      "name": "શ્રી ગીરધરનગર ઉપાશ્રય (શ્રી દરિયાપુરી આઠકોટી સ્થા. જૈન સંઘ છીપાપોળ સંચાલિત, શ્રી ગીરધરનગર શાહીબાગ સ્થા. જૈન સંઘ)",
      "address": "૧૦, સુભાષનગર બેન્ક ઓફ બરોડાની ગલીમાં, ગીરધરનગર, અમદાવાદ - ૪",
      "secretary_mobile": "9898520013",
      "sadhvis": [
        "તપસ્વી બા.બ્ર.પ.પૂ. હર્ષિતાબાઈ મ.સ.",
        "બા.બ્ર.પ.પૂ. રશ્મિતાબાઈ મ.સ.",
        "બા.બ્ર.પ.પૂ. નિપુણાબાઈ મ.સ.",
        "બા.બ્ર.પ.પૂ. કિરણબાઈ મ.સ.",
        "બા.બ્ર.પ.પૂ. પ્રતિક્ષાબાઈ મ.સ."
      ]
    },
    {
      "sr": 36,
      "nickname": "રાજસ્થાન ઉપાશ્રય (હઠીસિંગ)",
      "name": "श्री राजस्थान उपाश्रय (श्री राजस्थान स्थानकवासी जैन संघ)",
      "address": "हठीभाई की वाड़ी के सामने, शाहीबाग रोड, अहमदाबाद-380004",
      "secretary_mobile": "9898761509",
      "sadhvis": [
        "संयम साधिका श्री संयम प्रभाजी म.सा.",
        "स्वाध्याय शिला साध्वी श्री किरण प्रभाजी म.सा.",
        "मधुरव्याख्यानी सांध्वी श्री शशि प्रभाजी"
      ]
    },
    {
      "sr": 37,
      "nickname": "બાપુનગર ઉપાશ્રય",
      "name": "શ્રી બાપુનગર ઉપાશ્રય (શ્રી સ્થાનકવાસી જૈન સંઘ- બાપુનગર)",
      "address": "આદિનાથ ફ્લેટ, ઈન્દુલાલ યાજ્ઞિક હોલ પાછળ, વિમલનાથ જૈન દેરાસર રોડ, બાપુનગર, અંબર સિનેમા પાસે, અમદાવાદ - ૨૪",
      "secretary_mobile": "9824432390",
      "sadhvis": [
        "કાર્યકુશલા બા.બ્ર.પ.પૂ. કૌશલ્યાજી મ.સ.",
        "બા.બ્ર.પ.પૂ. શ્રી અર્પીતાજી મ.સ.",
        "બા.બ્ર.પ.પૂ. શ્રી નિધિબાઈ મ.સ.",
        "બા.બ્ર.પ.પૂ. શ્રી યશાજી મ.સ.",
        "બા.બ્ર.પ.પૂ. શ્રી ભવ્યાજી મ.સ."
      ]
    },
    {
      "sr": 38,
      "nickname": "કૃષ્ણનગર ઉપાશ્રય",
      "name": "શ્રી કૃષ્ણનગર ઉપાશ્રય (શ્રી કૃષ્ણનગર સ્થાનકવાસી જૈન સંઘ, પ.પૂ. માતૃશ્રી મણીબાઈ પ્રેમજી મેઘજી નિસર (કચ્છ વાડલા) સ્થા જૈન ઉપાશ્રય)",
      "address": "૯૨, ૯૪ જયાનંદ સોસાયટી પ્રિયા સિનેમા પાસે, ને.હા. ૮, કૃષ્ણનગર નરોડા રોડ, અમદાવાદ-૩૮૨૩૪૬",
      "secretary_mobile": "9426068802",
      "sadhvis": [
        "આત્મપ્રેમી બા.બ્ર.પ.પૂ. હર્ષાજી મ.સ.",
        "બા.બ્ર.પ.પૂ. મીરાજી મ.સ.",
        "બા.બ્ર.પ.પૂ. અલ્કાજી મ.સ.",
        "બા.બ્ર.પ.પૂ. ખંતીજી મ.સ.",
        "બા.બ્ર.પ.પૂ. રૂચિજી મ.સ."
      ]
    },
    {
      "sr": 39,
      "nickname": "છીપાપોળ ઉપાશ્રય",
      "name": "શ્રી છીપાપોળ ઉપાશ્રય (શ્રી દરિયાપુરી આઠ કોટી સ્થા. જૈન સંઘ)",
      "address": "સ્વામિનારાયણ મંદિર રોડ, છીપાપોળ, કાલુપુર, અમદાવાદ - ૩૮૦ ૦૦૧",
      "secretary_mobile": "9824024051",
      "sadhvis": [
        "શ્રમણી જયેષ્ઠ બા.બ્ર.પ.પૂ સુલોચનાબાઈ મ.સ.",
        "બા.બ્ર.પ.પૂ. દક્ષાબાઈ મ.સ."
      ]
    },
    {
      "sr": 40,
      "nickname": "સાબરમતી ઉપાશ્રય (હિરાણીનગર)",
      "name": "શ્રી શ્વેતામ્બર સ્થાનકવાસી જૈન સંઘ",
      "address": "હીરાણીનગર, કોમ્યુનીટી હોલની સામે, પોસ્ટ ઓફિસની પાછળ, સાબરમતી, અમદાવાદ - ૩૮૦ ૦૦૫",
      "secretary_mobile": "9426756418",
      "sadhvis": [
        "પ.પૂ. વંદિતાજી મ.સ.",
        "પ.પૂ. ચાંદનીજી મ.સ.",
        "પ.પૂ. રોશનીજી મ.સ.",
        "પ.પૂ. પ્રિયાંશીજી મ.સ.",
        "પ.પૂ. કાવ્યાંશીજી મ.સ.",
        "પ.પૂ. હિતાંશીજી મ.સ."
      ]
    },
    {
      "sr": 41,
      "nickname": "વર્ધમાન જ્ઞાન આરાધના ટ્રસ્ટ (રામનગર)",
      "name": "श्री वर्धमान ज्ञान आराधना ट्रस्ट",
      "address": "1135/8, अंबिकानगर, पानी की टांकी के पास, रामनगर, साबरमती, अहमदाबाद - 380 005",
      "secretary_mobile": "9426555698",
      "sadhvis": [
        "पूज्य महासतीजी श्री मनिताजी म.सा.",
        "पूज्य महासतीजी श्री प्रेरणाजी म.सा.",
        "पूज्य महासतीजी श्री शुद्धिजी म.सा.",
        "पूज्य महासतीजी श्री विशुद्धिजी म.सा."
      ]
    },
    {
      "sr": 42,
      "nickname": "ગાંધીનગર ઉપાશ્રય સે. ૬",
      "name": "શ્રી ગાંધીનગર સે.-૬ ઉપાશ્રય (વર્ધમાન સ્થાનકવાસી જૈન સંઘ)",
      "address": "પ્લોટ નંબર ૪૪૬-એ-૨ ધ-૨ સર્કલ, પેટ્રોલ પંપની પાછળ, અંબાજી માતાના ચોક પાસે, સેક્ટર-૬/એ, ગાંધીનગર",
      "secretary_mobile": "9898027973",
      "sadhvis": [
        "સેવાભાવી બા.બ્ર.પ.પૂ. જયંતિકાજી મ.સ.",
        "બા.બ્ર.પ.પૂ. ભાવિનીજી મ.સ.",
        "બા.બ્ર.પ.પૂ. વિજ્ઞાતાજી મ.સ.",
        "બા.બ્ર.પ.પૂ. લક્ષિતાજી મ.સ."
      ]
    },
    {
      "sr": 43,
      "nickname": "ગાંધીનગર ઉપાશ્રય સે. ૨૨",
      "name": "શ્રી ગાંધીનગર સે.-૨૨ ઉપાશ્રય (શ્રી ગાંધીનગર સ્થાનકવાસી જૈન સંઘ)",
      "address": "પ્લોટ નં. ૫૩૩, ગુરુકુળ પાસે, સેક્ટર નં.-૨૨ ગાંધીનગર-૩૮૨૦૨૧",
      "secretary_mobile": "9825032479",
      "sadhvis": [
        "પ.પૂ. મીતાજી મ.સ.",
        "પ.પૂ. ભારતીજી મ.સ.",
        "પ.પૂ. સુવ્રતાજી મ.સ.",
        "પ.પૂ. સુહાનીજી મ.સ."
      ]
    },
    {
      "sr": 44,
      "nickname": "વર્ધમાન સ્થા. જૈન સંઘ (ગોતા)",
      "name": "શ્રી વર્ધમાન સ્થાનકવાસી જૈન સંઘ ગોતા સંચાલિત (રાજેશ પ્રવિણચંદ્ર કસ્તુરચંદ શાહ (લોખંડવાળા) જૈન ઉપાશ્રય)",
      "address": "કામેશ્વર એલિગન્સની બાજુમાં, સ્વામિનારાયણ મંદિર પાસે, વંદે માતરમ રોડ, ગોતા, અમદાવાદ-૩૮૨૪૮૧",
      "secretary_mobile": "9428260780",
      "sadhvis": [
        "પૂ. શાશ્વતમુનિ મ.સા.",
        "પૂ. હરિશમુનિ મ.સા."
      ]
    },
    {
      "sr": 45,
      "nickname": "વર્ધમાન સ્થા. જૈન સંઘ (નવા નરોડા)",
      "name": "શ્રી નવા નરોડા ઉપાશ્રય (શ્રી વર્ધમાન સ્થાનકવાસી જૈન ટ્રસ્ટ (સંઘ))",
      "address": "૧૧, વેદાંત બંગ્લોઝ, રાજચંદ્ર ટેનામેન્ટ ની સામે, શેલ્બી હોસ્પિટલની પાસે, હરીદર્શન ચાર રસ્તા, નવા નરોડા, અમદાવાદ-૩૮૨૩૩૦",
      "secretary_mobile": "9157487700",
      "sadhvis": [
        "બા.બ્ર.પ.પૂ. સુધાજી મ.સ.",
        "બા.બ્ર.પ.પૂ. ધારીણીબાઈ મ.સ.",
        "બા.બ્ર.પ.પૂ. ઋજુતા મ.સ."
      ]
    },
    {
      "sr": 46,
      "nickname": "સુધર્મા સ્થા. જૈન સંઘ",
      "name": "શ્રી સુધર્મા સ્થાનકવાસી જૈન સંઘ",
      "address": "રાજ ચેમ્બર્સ, રાજા ભગત સ્કૂલની પાસે, ગોરનો કૂવો, મણિનગર (પૂર્વ), અમદાવાદ-૩૮૦૦૦૮",
      "secretary_mobile": "9825450933",
      "sadhvis": [
        "પ.પૂ. ચેતનમુનિ મ.સા.",
        "પ.પૂ. ચાંદનીબાઈ મ.સ.",
        "પ.પૂ. રોશનીબાઈ મ.સ."
      ]
    }
  ],
  "notes": [
    "All 46 organizations from the index have a corresponding detail page (page_04.png = org 1/booklet p9 through page_49.png = org 46/booklet p54); no detail pages were missing.",
    "Org 33 (ઘનશ્યામનગર ઉપાશ્રય, page_36) has no fixed ઠાણા/sadhvi roster printed — the page instead describes two visiting Mahasatijis for Paryushan, so sadhvis=[] for this org.",
    "Org 36 (રાજસ્થાન ઉપાશ્રય - હઠીસિંગ, page_39) and Org 41 (વર્ધમાન જ્ઞાન આરાધના ટ્રસ્ટ, page_44) are printed in Hindi/Devanagari script rather than Gujarati; name/address/sadhvis for these two are transcribed as printed (Hindi).",
    "Org 46 (સુધર્મા સ્થા. જૈન સંઘ, page_49) lists one muni (પ.પૂ. ચેતનમુનિ મ.સા.) together with two sadhvis under a combined ઠાણા list ('1' then 'અને' then '2,3'); all three were kept in the sadhvis array as printed since the page groups them together.",
    "The optional 'વિરતીધર ઉપાશ્રય' (booklet page 54-A) mentioned as possibly present was not found; the PDF/rendered pages end at page_49.png (booklet p54) with org 46, and there is no 47th detail page.",
    "Secretary mobile numbers were taken directly from the user-supplied index list (already in Arabic numerals) rather than re-derived from the Gujarati-numeral phone text on each page; spot checks (e.g. org 36, org 46) matched the printed page phone numbers.",
    "Address fields exclude phone/mobile numbers where they were embedded inline in the address text on the page, to keep the address field clean; some pages had multiple contact numbers (president/secretary/upashray) which were not all captured since only secretary_mobile was requested in the output schema."
  ]
}
